[
  {
    "id": "body-nv-legislature",
    "name": "Nevada Legislature",
    "jurisdiction": "Nevada",
    "level": "state",
    "website": "https://www.leg.state.nv.us/",
    "source_url": "https://www.leg.state.nv.us/app/calendar/a/",
    "meeting_index_url": "https://www.leg.state.nv.us/app/calendar/a/",
    "scraper_type": "html",
    "active": true,
    "seed_source_id": "nv-legislature",
    "notes": "Legislative meeting calendar and archived video should be treated as source-backed but structurally different from city agenda platforms.",
    "created_at": "2026-06-17T23:56:08.005Z",
    "updated_at": "2026-06-17T23:56:08.005Z"
  },
  {
    "id": "body-nv-governor-executive-boards",
    "name": "Governor / Executive Boards",
    "jurisdiction": "Nevada",
    "level": "state",
    "website": "https://www.gov.nv.gov/",
    "source_url": "https://www.gov.nv.gov/board-appts/",
    "meeting_index_url": "https://www.gov.nv.gov/board-appts/",
    "scraper_type": "manual",
    "active": true,
    "seed_source_id": "nv-governor-executive-boards",
    "notes": "Executive board records are distributed across appointed boards; use this as a registry seed until board-specific sources are added.",
    "created_at": "2026-06-17T23:56:08.005Z",
    "updated_at": "2026-06-17T23:56:08.005Z"
  },
  {
    "id": "body-carson-city-board-of-supervisors",
    "name": "Carson City Board of Supervisors",
    "jurisdiction": "Carson City, NV",
    "level": "city",
    "website": "https://www.carsoncity.gov/",
    "source_url": "https://www.carsoncity.gov/government/city-meetings",
    "meeting_index_url": "https://www.carsoncity.gov/government/city-meetings",
    "scraper_type": "granicus",
    "active": true,
    "seed_source_id": "carson-city-board-of-supervisors",
    "notes": "City meeting page exposes agendas, packets, minutes, motion records, and videos.",
    "created_at": "2026-06-17T23:56:08.005Z",
    "updated_at": "2026-06-17T23:56:08.005Z"
  },
  {
    "id": "body-reno-city-council",
    "name": "Reno City Council",
    "jurisdiction": "Reno, NV",
    "level": "city",
    "website": "https://www.reno.gov/government/city-council",
    "source_url": "https://reno.primegov.com/public/portal",
    "meeting_index_url": "https://reno.primegov.com/public/portal",
    "scraper_type": "granicus",
    "active": true,
    "seed_source_id": "reno-city-council",
    "notes": "Reno uses a PrimeGov/Granicus public portal for agendas and meeting records.",
    "created_at": "2026-06-17T23:56:08.005Z",
    "updated_at": "2026-06-17T23:56:08.005Z"
  },
  {
    "id": "body-sparks-city-council",
    "name": "Sparks City Council",
    "jurisdiction": "Sparks, NV",
    "level": "city",
    "website": "https://www.cityofsparks.us/your_government/public_meetings/city_council.php",
    "source_url": "https://www.cityofsparks.us/your_government/departments/city_clerk_and_records_management/city_council_meeting_agendas_and_minutes/index.php",
    "meeting_index_url": "https://www.cityofsparks.us/your_government/departments/city_clerk_and_records_management/city_council_meeting_agendas_and_minutes/index.php",
    "scraper_type": "html",
    "active": true,
    "seed_source_id": "sparks-city-council",
    "notes": "Agenda and minutes archive appears as city-hosted HTML/document links.",
    "created_at": "2026-06-17T23:56:08.005Z",
    "updated_at": "2026-06-17T23:56:08.005Z"
  },
  {
    "id": "body-washoe-county-commission",
    "name": "Washoe County Commission",
    "jurisdiction": "Washoe County, NV",
    "level": "county",
    "website": "https://www.washoecounty.gov/bcc/board_committees/index.php",
    "source_url": "https://washoe-nv.legistar.com/",
    "meeting_index_url": "https://washoe-nv.legistar.com/",
    "scraper_type": "legistar",
    "active": true,
    "seed_source_id": "washoe-county-commission",
    "notes": "Legistar source should eventually provide structured agenda items and vote records.",
    "created_at": "2026-06-17T23:56:08.005Z",
    "updated_at": "2026-06-17T23:56:08.005Z"
  },
  {
    "id": "body-clark-county-commission",
    "name": "Clark County Commission",
    "jurisdiction": "Clark County, NV",
    "level": "county",
    "website": "https://www.clarkcountynv.gov/government/board_of_county_commissioners/county-meeting-agendas",
    "source_url": "https://clark.legistar.com/",
    "meeting_index_url": "https://clark.legistar.com/",
    "scraper_type": "legistar",
    "active": true,
    "seed_source_id": "clark-county-commission",
    "notes": "County page links agendas while Legistar is the structured meeting system.",
    "created_at": "2026-06-17T23:56:08.005Z",
    "updated_at": "2026-06-17T23:56:08.005Z"
  },
  {
    "id": "body-las-vegas-city-council",
    "name": "Las Vegas City Council",
    "jurisdiction": "Las Vegas, NV",
    "level": "city",
    "website": "https://www.lasvegasnevada.gov/Government/Meetings",
    "source_url": "https://lasvegas.primegov.com/public/portal",
    "meeting_index_url": "https://lasvegas.primegov.com/public/portal",
    "scraper_type": "granicus",
    "active": true,
    "seed_source_id": "las-vegas-city-council",
    "notes": "PrimeGov portal seed for agenda and packet discovery.",
    "created_at": "2026-06-17T23:56:08.005Z",
    "updated_at": "2026-06-17T23:56:08.005Z"
  },
  {
    "id": "body-henderson-city-council",
    "name": "Henderson City Council",
    "jurisdiction": "Henderson, NV",
    "level": "city",
    "website": "https://www.cityofhenderson.com/",
    "source_url": "https://www.cityofhenderson.com/government/public-meeting-agendas",
    "meeting_index_url": "https://www.cityofhenderson.com/government/public-meeting-agendas",
    "scraper_type": "html",
    "active": true,
    "seed_source_id": "henderson-city-council",
    "notes": "Public meeting agendas page is the first-stage discovery target.",
    "created_at": "2026-06-17T23:56:08.005Z",
    "updated_at": "2026-06-17T23:56:08.005Z"
  },
  {
    "id": "body-north-las-vegas-city-council",
    "name": "North Las Vegas City Council",
    "jurisdiction": "North Las Vegas, NV",
    "level": "city",
    "website": "https://www.cityofnorthlasvegas.com/",
    "source_url": "https://www.cityofnorthlasvegas.com/our-city/meetings-and-agendas",
    "meeting_index_url": "https://www.cityofnorthlasvegas.com/our-city/meetings-and-agendas",
    "scraper_type": "granicus",
    "active": true,
    "seed_source_id": "north-las-vegas-city-council",
    "notes": "City page points to a PrimeGov portal for meeting records.",
    "created_at": "2026-06-17T23:56:08.005Z",
    "updated_at": "2026-06-17T23:56:08.005Z"
  },
  {
    "id": "body-washoe-county-school-district",
    "name": "Washoe County School District Board of Trustees",
    "jurisdiction": "Washoe County School District, NV",
    "level": "school",
    "website": "https://www.washoeschools.net/trustees",
    "source_url": "https://www.washoeschools.net/trustees/board-of-trustees/board-meetings-calendar",
    "meeting_index_url": "https://www.washoeschools.net/trustees/board-of-trustees/board-meetings-calendar",
    "scraper_type": "html",
    "active": true,
    "seed_source_id": "washoe-county-school-district",
    "notes": "School district calendar and archive are HTML first-stage sources.",
    "created_at": "2026-06-17T23:56:08.005Z",
    "updated_at": "2026-06-17T23:56:08.005Z"
  },
  {
    "id": "body-clark-county-school-district",
    "name": "Clark County School District Board of Trustees",
    "jurisdiction": "Clark County School District, NV",
    "level": "school",
    "website": "https://www.ccsd.net/",
    "source_url": "https://www.boarddocs.com/nv/ccsdlv/Board.nsf/Public",
    "meeting_index_url": "https://www.boarddocs.com/nv/ccsdlv/Board.nsf/Public",
    "scraper_type": "html",
    "active": true,
    "seed_source_id": "clark-county-school-district",
    "notes": "BoardDocs support belongs in the later automated scraper phase; keep as HTML/manual source until then.",
    "created_at": "2026-06-17T23:56:08.005Z",
    "updated_at": "2026-06-17T23:56:08.005Z"
  },
  {
    "id": "body-carson-city-school-district",
    "name": "Carson City School District Board of Trustees",
    "jurisdiction": "Carson City School District, NV",
    "level": "school",
    "website": "https://www.carsoncityschools.com/our-district/school-board",
    "source_url": "https://www.carsoncityschools.com/our-district/school-board",
    "meeting_index_url": "https://www.carsoncityschools.com/our-district/school-board",
    "scraper_type": "html",
    "active": true,
    "seed_source_id": "carson-city-school-district",
    "notes": "District page plus BoardDocs archive seed.",
    "created_at": "2026-06-17T23:56:08.005Z",
    "updated_at": "2026-06-17T23:56:08.005Z"
  },
  {
    "id": "body-nshe-board-of-regents",
    "name": "Nevada System of Higher Education Board of Regents",
    "jurisdiction": "Nevada System of Higher Education",
    "level": "university",
    "website": "https://nshe.nevada.edu/regents/",
    "source_url": "https://nshe.nevada.edu/regents/upcoming-meetings/",
    "meeting_index_url": "https://nshe.nevada.edu/regents/upcoming-meetings/",
    "scraper_type": "html",
    "active": true,
    "seed_source_id": "nshe-board-of-regents",
    "notes": "Regents pages include upcoming meetings and archives with agenda materials.",
    "created_at": "2026-06-17T23:56:08.005Z",
    "updated_at": "2026-06-17T23:56:08.005Z"
  },
  {
    "id": "body-carson-city-board-of-supervisors-9-1-1-surcharge-advisory-committee",
    "name": "9-1-1 Surcharge Advisory Committee",
    "jurisdiction": "Carson City, NV",
    "level": "city",
    "website": null,
    "source_url": "https://carsoncity.granicus.com/AgendaViewer.php?view_id=2&clip_id=2482",
    "meeting_index_url": "https://carsoncity.granicus.com/AgendaViewer.php?view_id=2&clip_id=2482",
    "scraper_type": "html",
    "active": true,
    "seed_source_id": "carson-city-board-of-supervisors",
    "notes": "Discovered from 9-1-1 Surcharge Advisory Committee historical meeting archive.",
    "created_at": "2026-06-17T23:56:08.004Z",
    "updated_at": "2026-06-17T23:56:08.004Z"
  },
  {
    "id": "body-carson-city-board-of-supervisors-admin-appeal-hearing",
    "name": "Admin Appeal Hearing",
    "jurisdiction": "Carson City, NV",
    "level": "city",
    "website": null,
    "source_url": "https://carsoncity.granicus.com/MinutesViewer.php?view_id=2&clip_id=2621&doc_id=b0073a2d-4003-11f0-b7f5-005056a89546",
    "meeting_index_url": "https://carsoncity.granicus.com/MinutesViewer.php?view_id=2&clip_id=2621&doc_id=b0073a2d-4003-11f0-b7f5-005056a89546",
    "scraper_type": "html",
    "active": true,
    "seed_source_id": "carson-city-board-of-supervisors",
    "notes": "Discovered from Admin Appeal Hearing historical meeting archive.",
    "created_at": "2026-06-17T23:56:08.004Z",
    "updated_at": "2026-06-17T23:56:08.004Z"
  },
  {
    "id": "body-carson-city-board-of-supervisors-administrative-hearing",
    "name": "Administrative Hearing",
    "jurisdiction": "Carson City, NV",
    "level": "city",
    "website": null,
    "source_url": "https://carsoncity.granicus.com/AgendaViewer.php?view_id=2&clip_id=2582",
    "meeting_index_url": "https://carsoncity.granicus.com/AgendaViewer.php?view_id=2&clip_id=2582",
    "scraper_type": "html",
    "active": true,
    "seed_source_id": "carson-city-board-of-supervisors",
    "notes": "Discovered from Administrative Hearing historical meeting archive.",
    "created_at": "2026-06-17T23:56:08.004Z",
    "updated_at": "2026-06-17T23:56:08.004Z"
  },
  {
    "id": "body-carson-city-board-of-supervisors-administrative-permit-review",
    "name": "Administrative Permit Review",
    "jurisdiction": "Carson City, NV",
    "level": "city",
    "website": null,
    "source_url": "https://carsoncity.granicus.com/AgendaViewer.php?view_id=2&clip_id=2561",
    "meeting_index_url": "https://carsoncity.granicus.com/AgendaViewer.php?view_id=2&clip_id=2561",
    "scraper_type": "html",
    "active": true,
    "seed_source_id": "carson-city-board-of-supervisors",
    "notes": "Discovered from Administrative Permit Review historical meeting archive.",
    "created_at": "2026-06-17T23:56:08.004Z",
    "updated_at": "2026-06-17T23:56:08.004Z"
  },
  {
    "id": "body-carson-city-board-of-supervisors-carson-city-advisory-board-to-manage-wildlife",
    "name": "Carson City Advisory Board to Manage Wildlife",
    "jurisdiction": "Carson City, NV",
    "level": "city",
    "website": null,
    "source_url": "https://carsoncity.granicus.com/AgendaViewer.php?view_id=2&clip_id=2596",
    "meeting_index_url": "https://carsoncity.granicus.com/AgendaViewer.php?view_id=2&clip_id=2596",
    "scraper_type": "html",
    "active": true,
    "seed_source_id": "carson-city-board-of-supervisors",
    "notes": "Discovered from Carson City Advisory Board to Manage Wildlife historical meeting archive.",
    "created_at": "2026-06-17T23:56:08.004Z",
    "updated_at": "2026-06-17T23:56:08.004Z"
  },
  {
    "id": "body-carson-city-board-of-supervisors-advisory-board-to-manage-wildlife",
    "name": "Advisory Board to Manage Wildlife",
    "jurisdiction": "Carson City, NV",
    "level": "city",
    "website": null,
    "source_url": "https://carsoncity.granicus.com/AgendaViewer.php?view_id=2&clip_id=2358",
    "meeting_index_url": "https://carsoncity.granicus.com/AgendaViewer.php?view_id=2&clip_id=2358",
    "scraper_type": "html",
    "active": true,
    "seed_source_id": "carson-city-board-of-supervisors",
    "notes": "Discovered from Advisory Board to Manage Wildlife historical meeting archive.",
    "created_at": "2026-06-17T23:56:08.004Z",
    "updated_at": "2026-06-17T23:56:08.004Z"
  },
  {
    "id": "body-carson-city-board-of-supervisors-airport-authority",
    "name": "Airport Authority",
    "jurisdiction": "Carson City, NV",
    "level": "city",
    "website": null,
    "source_url": "https://carsoncity.granicus.com/AgendaViewer.php?view_id=2&clip_id=2356",
    "meeting_index_url": "https://carsoncity.granicus.com/AgendaViewer.php?view_id=2&clip_id=2356",
    "scraper_type": "html",
    "active": true,
    "seed_source_id": "carson-city-board-of-supervisors",
    "notes": "Discovered from Airport Authority historical meeting archive.",
    "created_at": "2026-06-17T23:56:08.004Z",
    "updated_at": "2026-06-17T23:56:08.004Z"
  },
  {
    "id": "body-carson-city-board-of-supervisors-airport-authority-special-meeting",
    "name": "Airport Authority Special Meeting",
    "jurisdiction": "Carson City, NV",
    "level": "city",
    "website": null,
    "source_url": "https://carsoncity.granicus.com/AgendaViewer.php?view_id=2&clip_id=2446",
    "meeting_index_url": "https://carsoncity.granicus.com/AgendaViewer.php?view_id=2&clip_id=2446",
    "scraper_type": "html",
    "active": true,
    "seed_source_id": "carson-city-board-of-supervisors",
    "notes": "Discovered from Airport Authority Special Meeting historical meeting archive.",
    "created_at": "2026-06-17T23:56:08.004Z",
    "updated_at": "2026-06-17T23:56:08.004Z"
  },
  {
    "id": "body-carson-city-board-of-supervisors-audit-committee",
    "name": "Audit Committee",
    "jurisdiction": "Carson City, NV",
    "level": "city",
    "website": null,
    "source_url": "https://carsoncity.granicus.com/AgendaViewer.php?view_id=2&clip_id=2349",
    "meeting_index_url": "https://carsoncity.granicus.com/AgendaViewer.php?view_id=2&clip_id=2349",
    "scraper_type": "html",
    "active": true,
    "seed_source_id": "carson-city-board-of-supervisors",
    "notes": "Discovered from Audit Committee historical meeting archive.",
    "created_at": "2026-06-17T23:56:08.004Z",
    "updated_at": "2026-06-17T23:56:08.004Z"
  },
  {
    "id": "body-carson-city-board-of-supervisors-board-of-appeals",
    "name": "Board of Appeals",
    "jurisdiction": "Carson City, NV",
    "level": "city",
    "website": null,
    "source_url": "https://carsoncity.granicus.com/AgendaViewer.php?view_id=2&clip_id=2790",
    "meeting_index_url": "https://carsoncity.granicus.com/AgendaViewer.php?view_id=2&clip_id=2790",
    "scraper_type": "html",
    "active": true,
    "seed_source_id": "carson-city-board-of-supervisors",
    "notes": "Discovered from Board of Appeals historical meeting archive.",
    "created_at": "2026-06-17T23:56:08.004Z",
    "updated_at": "2026-06-17T23:56:08.004Z"
  },
  {
    "id": "body-carson-city-board-of-supervisors-board-of-equalization",
    "name": "Board of Equalization",
    "jurisdiction": "Carson City, NV",
    "level": "city",
    "website": null,
    "source_url": "https://carsoncity.granicus.com/AgendaViewer.php?view_id=2&clip_id=2370",
    "meeting_index_url": "https://carsoncity.granicus.com/AgendaViewer.php?view_id=2&clip_id=2370",
    "scraper_type": "html",
    "active": true,
    "seed_source_id": "carson-city-board-of-supervisors",
    "notes": "Discovered from Board of Equalization historical meeting archive.",
    "created_at": "2026-06-17T23:56:08.004Z",
    "updated_at": "2026-06-17T23:56:08.004Z"
  },
  {
    "id": "body-carson-city-board-of-supervisors-board-of-supervisors-and-board-of-health",
    "name": "Board of Supervisors and Board of Health",
    "jurisdiction": "Carson City, NV",
    "level": "city",
    "website": null,
    "source_url": "https://carsoncity.granicus.com/AgendaViewer.php?view_id=2&clip_id=2389",
    "meeting_index_url": "https://carsoncity.granicus.com/AgendaViewer.php?view_id=2&clip_id=2389",
    "scraper_type": "html",
    "active": true,
    "seed_source_id": "carson-city-board-of-supervisors",
    "notes": "Discovered from Board of Supervisors and Board of Health historical meeting archive.",
    "created_at": "2026-06-17T23:56:08.004Z",
    "updated_at": "2026-06-17T23:56:08.004Z"
  },
  {
    "id": "body-carson-city-board-of-supervisors-board-of-supervisors-and-redevelopment-authority",
    "name": "Board of Supervisors and Redevelopment Authority",
    "jurisdiction": "Carson City, NV",
    "level": "city",
    "website": null,
    "source_url": "https://carsoncity.granicus.com/AgendaViewer.php?view_id=2&clip_id=2347",
    "meeting_index_url": "https://carsoncity.granicus.com/AgendaViewer.php?view_id=2&clip_id=2347",
    "scraper_type": "html",
    "active": true,
    "seed_source_id": "carson-city-board-of-supervisors",
    "notes": "Discovered from Board of Supervisors and Redevelopment Authority historical meeting archive.",
    "created_at": "2026-06-17T23:56:08.004Z",
    "updated_at": "2026-06-17T23:56:08.004Z"
  },
  {
    "id": "body-carson-city-board-of-supervisors-board-of-supervisors",
    "name": "Board of Supervisors",
    "jurisdiction": "Carson City, NV",
    "level": "city",
    "website": null,
    "source_url": "https://carsoncity.granicus.com/AgendaViewer.php?view_id=2&clip_id=2376",
    "meeting_index_url": "https://carsoncity.granicus.com/AgendaViewer.php?view_id=2&clip_id=2376",
    "scraper_type": "html",
    "active": true,
    "seed_source_id": "carson-city-board-of-supervisors",
    "notes": "Discovered from Board of Supervisors historical meeting archive.",
    "created_at": "2026-06-17T23:56:08.004Z",
    "updated_at": "2026-06-17T23:56:08.004Z"
  },
  {
    "id": "body-carson-city-board-of-supervisors-board-of-supervisors-work-session",
    "name": "Board of Supervisors Work Session",
    "jurisdiction": "Carson City, NV",
    "level": "city",
    "website": null,
    "source_url": "https://carsoncity.granicus.com/AgendaViewer.php?view_id=2&clip_id=2832",
    "meeting_index_url": "https://carsoncity.granicus.com/AgendaViewer.php?view_id=2&clip_id=2832",
    "scraper_type": "html",
    "active": true,
    "seed_source_id": "carson-city-board-of-supervisors",
    "notes": "Discovered from Board of Supervisors Work Session historical meeting archive.",
    "created_at": "2026-06-17T23:56:08.004Z",
    "updated_at": "2026-06-17T23:56:08.004Z"
  },
  {
    "id": "body-carson-city-board-of-supervisors-board-of-supervisors-and-redevelopment-authority-and-board-of-health",
    "name": "Board of Supervisors and Redevelopment Authority and Board of Health",
    "jurisdiction": "Carson City, NV",
    "level": "city",
    "website": null,
    "source_url": "https://carsoncity.granicus.com/AgendaViewer.php?view_id=2&clip_id=2451",
    "meeting_index_url": "https://carsoncity.granicus.com/AgendaViewer.php?view_id=2&clip_id=2451",
    "scraper_type": "html",
    "active": true,
    "seed_source_id": "carson-city-board-of-supervisors",
    "notes": "Discovered from Board of Supervisors and Redevelopment Authority and Board of Health historical meeting archive.",
    "created_at": "2026-06-17T23:56:08.004Z",
    "updated_at": "2026-06-17T23:56:08.004Z"
  },
  {
    "id": "body-carson-city-board-of-supervisors-work-session-of-the-board-of-supervisors",
    "name": "Work Session of the Board of Supervisors",
    "jurisdiction": "Carson City, NV",
    "level": "city",
    "website": null,
    "source_url": "https://carsoncity.granicus.com/AgendaViewer.php?view_id=2&clip_id=2622",
    "meeting_index_url": "https://carsoncity.granicus.com/AgendaViewer.php?view_id=2&clip_id=2622",
    "scraper_type": "html",
    "active": true,
    "seed_source_id": "carson-city-board-of-supervisors",
    "notes": "Discovered from Work Session of the Board of Supervisors historical meeting archive.",
    "created_at": "2026-06-17T23:56:08.004Z",
    "updated_at": "2026-06-17T23:56:08.004Z"
  },
  {
    "id": "body-carson-city-board-of-supervisors-board-of-supervisors-and-liquor-and-entertainment-board",
    "name": "Board of Supervisors and Liquor and Entertainment Board",
    "jurisdiction": "Carson City, NV",
    "level": "city",
    "website": null,
    "source_url": "https://carsoncity.granicus.com/AgendaViewer.php?view_id=2&clip_id=2368",
    "meeting_index_url": "https://carsoncity.granicus.com/AgendaViewer.php?view_id=2&clip_id=2368",
    "scraper_type": "html",
    "active": true,
    "seed_source_id": "carson-city-board-of-supervisors",
    "notes": "Discovered from Board of Supervisors and Liquor and Entertainment Board historical meeting archive.",
    "created_at": "2026-06-17T23:56:08.004Z",
    "updated_at": "2026-06-17T23:56:08.004Z"
  },
  {
    "id": "body-carson-city-board-of-supervisors-board-of-supervisors-and-the-joint-meeting-of-the-board-of-supervisors-and-the-planning-commissi",
    "name": "Board of Supervisors and the Joint Meeting of the Board of Supervisors and the Planning Commission",
    "jurisdiction": "Carson City, NV",
    "level": "city",
    "website": null,
    "source_url": "https://carsoncity.granicus.com/AgendaViewer.php?view_id=2&clip_id=2586",
    "meeting_index_url": "https://carsoncity.granicus.com/AgendaViewer.php?view_id=2&clip_id=2586",
    "scraper_type": "html",
    "active": true,
    "seed_source_id": "carson-city-board-of-supervisors",
    "notes": "Discovered from Board of Supervisors and the Joint Meeting of the Board of Supervisors and the Planning Commission historical meeting archive.",
    "created_at": "2026-06-17T23:56:08.004Z",
    "updated_at": "2026-06-17T23:56:08.004Z"
  },
  {
    "id": "body-carson-city-board-of-supervisors-board-of-supervisors-and-the-planning-commission",
    "name": "Board of Supervisors and the Planning Commission",
    "jurisdiction": "Carson City, NV",
    "level": "city",
    "website": null,
    "source_url": "https://carsoncity.granicus.com/AgendaViewer.php?view_id=2&clip_id=2361",
    "meeting_index_url": "https://carsoncity.granicus.com/AgendaViewer.php?view_id=2&clip_id=2361",
    "scraper_type": "html",
    "active": true,
    "seed_source_id": "carson-city-board-of-supervisors",
    "notes": "Discovered from Board of Supervisors and the Planning Commission historical meeting archive.",
    "created_at": "2026-06-17T23:56:08.004Z",
    "updated_at": "2026-06-17T23:56:08.004Z"
  },
  {
    "id": "body-carson-city-board-of-supervisors-board-of-supervisors-and-regional-transportation-commission-work-sessions",
    "name": "Board of Supervisors & Regional Transportation Commission Work Sessions",
    "jurisdiction": "Carson City, NV",
    "level": "city",
    "website": null,
    "source_url": "https://carsoncity.granicus.com/AgendaViewer.php?view_id=2&clip_id=2406",
    "meeting_index_url": "https://carsoncity.granicus.com/AgendaViewer.php?view_id=2&clip_id=2406",
    "scraper_type": "html",
    "active": true,
    "seed_source_id": "carson-city-board-of-supervisors",
    "notes": "Discovered from Board of Supervisors & Regional Transportation Commission Work Sessions historical meeting archive.",
    "created_at": "2026-06-17T23:56:08.004Z",
    "updated_at": "2026-06-17T23:56:08.004Z"
  },
  {
    "id": "body-carson-city-board-of-supervisors-carson-area-metropolitan-planning-organization",
    "name": "Carson Area Metropolitan Planning Organization",
    "jurisdiction": "Carson City, NV",
    "level": "city",
    "website": null,
    "source_url": "https://carsoncity.granicus.com/AgendaViewer.php?view_id=2&clip_id=2393",
    "meeting_index_url": "https://carsoncity.granicus.com/AgendaViewer.php?view_id=2&clip_id=2393",
    "scraper_type": "html",
    "active": true,
    "seed_source_id": "carson-city-board-of-supervisors",
    "notes": "Discovered from Carson Area Metropolitan Planning Organization historical meeting archive.",
    "created_at": "2026-06-17T23:56:08.004Z",
    "updated_at": "2026-06-17T23:56:08.004Z"
  },
  {
    "id": "body-carson-city-board-of-supervisors-carson-city-culture-and-tourism-authority",
    "name": "Carson City Culture & Tourism Authority",
    "jurisdiction": "Carson City, NV",
    "level": "city",
    "website": null,
    "source_url": "https://carsoncity.granicus.com/AgendaViewer.php?view_id=2&clip_id=2348",
    "meeting_index_url": "https://carsoncity.granicus.com/AgendaViewer.php?view_id=2&clip_id=2348",
    "scraper_type": "html",
    "active": true,
    "seed_source_id": "carson-city-board-of-supervisors",
    "notes": "Discovered from Carson City Culture & Tourism Authority historical meeting archive.",
    "created_at": "2026-06-17T23:56:08.004Z",
    "updated_at": "2026-06-17T23:56:08.004Z"
  },
  {
    "id": "body-carson-city-board-of-supervisors-other-post-employment-benefits-trust-fund-board-of-trustees",
    "name": "Other Post Employment Benefits Trust Fund Board of Trustees",
    "jurisdiction": "Carson City, NV",
    "level": "city",
    "website": null,
    "source_url": "https://carsoncity.granicus.com/AgendaViewer.php?view_id=2&clip_id=2380",
    "meeting_index_url": "https://carsoncity.granicus.com/AgendaViewer.php?view_id=2&clip_id=2380",
    "scraper_type": "html",
    "active": true,
    "seed_source_id": "carson-city-board-of-supervisors",
    "notes": "Discovered from Other Post Employment Benefits Trust Fund Board of Trustees historical meeting archive.",
    "created_at": "2026-06-17T23:56:08.004Z",
    "updated_at": "2026-06-17T23:56:08.004Z"
  },
  {
    "id": "body-carson-city-board-of-supervisors-carson-city-school-board",
    "name": "Carson City School Board",
    "jurisdiction": "Carson City, NV",
    "level": "city",
    "website": null,
    "source_url": "https://carsoncity.granicus.com/AgendaViewer.php?view_id=2&clip_id=2350",
    "meeting_index_url": "https://carsoncity.granicus.com/AgendaViewer.php?view_id=2&clip_id=2350",
    "scraper_type": "html",
    "active": true,
    "seed_source_id": "carson-city-board-of-supervisors",
    "notes": "Discovered from Carson City School Board historical meeting archive.",
    "created_at": "2026-06-17T23:56:08.004Z",
    "updated_at": "2026-06-17T23:56:08.004Z"
  },
  {
    "id": "body-carson-city-board-of-supervisors-carson-city-school-board-employee-of-the-year",
    "name": "Carson City School Board Employee of the Year",
    "jurisdiction": "Carson City, NV",
    "level": "city",
    "website": null,
    "source_url": "https://carsoncity.granicus.com/MediaPlayer.php?view_id=2&clip_id=2867",
    "meeting_index_url": "https://carsoncity.granicus.com/MediaPlayer.php?view_id=2&clip_id=2867",
    "scraper_type": "html",
    "active": true,
    "seed_source_id": "carson-city-board-of-supervisors",
    "notes": "Discovered from Carson City School Board Employee of the Year historical meeting archive.",
    "created_at": "2026-06-17T23:56:08.004Z",
    "updated_at": "2026-06-17T23:56:08.004Z"
  },
  {
    "id": "body-carson-city-board-of-supervisors-school-district-2025-employees-of-the-year",
    "name": "School District 2025 Employees of the Year",
    "jurisdiction": "Carson City, NV",
    "level": "city",
    "website": null,
    "source_url": "https://carsoncity.granicus.com/MediaPlayer.php?view_id=2&clip_id=2654",
    "meeting_index_url": "https://carsoncity.granicus.com/MediaPlayer.php?view_id=2&clip_id=2654",
    "scraper_type": "html",
    "active": true,
    "seed_source_id": "carson-city-board-of-supervisors",
    "notes": "Discovered from School District 2025 Employees of the Year historical meeting archive.",
    "created_at": "2026-06-17T23:56:08.004Z",
    "updated_at": "2026-06-17T23:56:08.004Z"
  },
  {
    "id": "body-carson-city-board-of-supervisors-charter-review-committee",
    "name": "Charter Review Committee",
    "jurisdiction": "Carson City, NV",
    "level": "city",
    "website": null,
    "source_url": "https://carsoncity.granicus.com/AgendaViewer.php?view_id=2&clip_id=2396",
    "meeting_index_url": "https://carsoncity.granicus.com/AgendaViewer.php?view_id=2&clip_id=2396",
    "scraper_type": "html",
    "active": true,
    "seed_source_id": "carson-city-board-of-supervisors",
    "notes": "Discovered from Charter Review Committee historical meeting archive.",
    "created_at": "2026-06-17T23:56:08.004Z",
    "updated_at": "2026-06-17T23:56:08.004Z"
  },
  {
    "id": "body-carson-city-board-of-supervisors-cultural-commission",
    "name": "Cultural Commission",
    "jurisdiction": "Carson City, NV",
    "level": "city",
    "website": null,
    "source_url": "https://carsoncity.granicus.com/AgendaViewer.php?view_id=2&clip_id=2391",
    "meeting_index_url": "https://carsoncity.granicus.com/AgendaViewer.php?view_id=2&clip_id=2391",
    "scraper_type": "html",
    "active": true,
    "seed_source_id": "carson-city-board-of-supervisors",
    "notes": "Discovered from Cultural Commission historical meeting archive.",
    "created_at": "2026-06-17T23:56:08.004Z",
    "updated_at": "2026-06-17T23:56:08.004Z"
  },
  {
    "id": "body-carson-city-board-of-supervisors-debt-management-commission",
    "name": "Debt Management Commission",
    "jurisdiction": "Carson City, NV",
    "level": "city",
    "website": null,
    "source_url": "https://carsoncity.granicus.com/AgendaViewer.php?view_id=2&clip_id=2378",
    "meeting_index_url": "https://carsoncity.granicus.com/AgendaViewer.php?view_id=2&clip_id=2378",
    "scraper_type": "html",
    "active": true,
    "seed_source_id": "carson-city-board-of-supervisors",
    "notes": "Discovered from Debt Management Commission historical meeting archive.",
    "created_at": "2026-06-17T23:56:08.004Z",
    "updated_at": "2026-06-17T23:56:08.004Z"
  },
  {
    "id": "body-carson-city-board-of-supervisors-historic-resources-commission",
    "name": "Historic Resources Commission",
    "jurisdiction": "Carson City, NV",
    "level": "city",
    "website": null,
    "source_url": "https://carsoncity.granicus.com/AgendaViewer.php?view_id=2&clip_id=2346",
    "meeting_index_url": "https://carsoncity.granicus.com/AgendaViewer.php?view_id=2&clip_id=2346",
    "scraper_type": "html",
    "active": true,
    "seed_source_id": "carson-city-board-of-supervisors",
    "notes": "Discovered from Historic Resources Commission historical meeting archive.",
    "created_at": "2026-06-17T23:56:08.004Z",
    "updated_at": "2026-06-17T23:56:08.004Z"
  },
  {
    "id": "body-carson-city-board-of-supervisors-library-board-of-trustees",
    "name": "Library Board of Trustees",
    "jurisdiction": "Carson City, NV",
    "level": "city",
    "website": null,
    "source_url": "https://carsoncity.granicus.com/AgendaViewer.php?view_id=2&clip_id=2382",
    "meeting_index_url": "https://carsoncity.granicus.com/AgendaViewer.php?view_id=2&clip_id=2382",
    "scraper_type": "html",
    "active": true,
    "seed_source_id": "carson-city-board-of-supervisors",
    "notes": "Discovered from Library Board of Trustees historical meeting archive.",
    "created_at": "2026-06-17T23:56:08.004Z",
    "updated_at": "2026-06-17T23:56:08.004Z"
  },
  {
    "id": "body-carson-city-board-of-supervisors-liquor-hearings-officer",
    "name": "Liquor Hearings Officer",
    "jurisdiction": "Carson City, NV",
    "level": "city",
    "website": null,
    "source_url": "https://carsoncity.granicus.com/AgendaViewer.php?view_id=2&clip_id=2473",
    "meeting_index_url": "https://carsoncity.granicus.com/AgendaViewer.php?view_id=2&clip_id=2473",
    "scraper_type": "html",
    "active": true,
    "seed_source_id": "carson-city-board-of-supervisors",
    "notes": "Discovered from Liquor Hearings Officer historical meeting archive.",
    "created_at": "2026-06-17T23:56:08.004Z",
    "updated_at": "2026-06-17T23:56:08.004Z"
  },
  {
    "id": "body-carson-city-board-of-supervisors-local-emergency-planning-committee",
    "name": "Local Emergency Planning Committee",
    "jurisdiction": "Carson City, NV",
    "level": "city",
    "website": null,
    "source_url": "https://carsoncity.granicus.com/AgendaViewer.php?view_id=2&clip_id=2545",
    "meeting_index_url": "https://carsoncity.granicus.com/AgendaViewer.php?view_id=2&clip_id=2545",
    "scraper_type": "html",
    "active": true,
    "seed_source_id": "carson-city-board-of-supervisors",
    "notes": "Discovered from Local Emergency Planning Committee historical meeting archive.",
    "created_at": "2026-06-17T23:56:08.004Z",
    "updated_at": "2026-06-17T23:56:08.004Z"
  },
  {
    "id": "body-carson-city-board-of-supervisors-nv-commission-for-reconstruction-of-v-and-t-railway",
    "name": "NV Commission for Reconstruction of V&T Railway",
    "jurisdiction": "Carson City, NV",
    "level": "city",
    "website": null,
    "source_url": "https://carsoncity.granicus.com/AgendaViewer.php?view_id=2&clip_id=2360",
    "meeting_index_url": "https://carsoncity.granicus.com/AgendaViewer.php?view_id=2&clip_id=2360",
    "scraper_type": "html",
    "active": true,
    "seed_source_id": "carson-city-board-of-supervisors",
    "notes": "Discovered from NV Commission for Reconstruction of V&T Railway historical meeting archive.",
    "created_at": "2026-06-17T23:56:08.004Z",
    "updated_at": "2026-06-17T23:56:08.004Z"
  },
  {
    "id": "body-carson-city-board-of-supervisors-open-space-advisory-committee",
    "name": "Open Space Advisory Committee",
    "jurisdiction": "Carson City, NV",
    "level": "city",
    "website": null,
    "source_url": "https://carsoncity.granicus.com/AgendaViewer.php?view_id=2&clip_id=2379",
    "meeting_index_url": "https://carsoncity.granicus.com/AgendaViewer.php?view_id=2&clip_id=2379",
    "scraper_type": "html",
    "active": true,
    "seed_source_id": "carson-city-board-of-supervisors",
    "notes": "Discovered from Open Space Advisory Committee historical meeting archive.",
    "created_at": "2026-06-17T23:56:08.004Z",
    "updated_at": "2026-06-17T23:56:08.004Z"
  },
  {
    "id": "body-carson-city-board-of-supervisors-joint-meeting-of-the-open-space-advisory-committee-and-the-parks-and-recreation-commission",
    "name": "Joint Meeting of the Open Space Advisory Committee & the Parks and Recreation Commission",
    "jurisdiction": "Carson City, NV",
    "level": "city",
    "website": null,
    "source_url": "https://carsoncity.granicus.com/AgendaViewer.php?view_id=2&clip_id=2690",
    "meeting_index_url": "https://carsoncity.granicus.com/AgendaViewer.php?view_id=2&clip_id=2690",
    "scraper_type": "html",
    "active": true,
    "seed_source_id": "carson-city-board-of-supervisors",
    "notes": "Discovered from Joint Meeting of the Open Space Advisory Committee & the Parks and Recreation Commission historical meeting archive.",
    "created_at": "2026-06-17T23:56:08.004Z",
    "updated_at": "2026-06-17T23:56:08.004Z"
  },
  {
    "id": "body-carson-city-board-of-supervisors-parks-and-recreation-commission",
    "name": "Parks and Recreation Commission",
    "jurisdiction": "Carson City, NV",
    "level": "city",
    "website": null,
    "source_url": "https://carsoncity.granicus.com/AgendaViewer.php?view_id=2&clip_id=2366",
    "meeting_index_url": "https://carsoncity.granicus.com/AgendaViewer.php?view_id=2&clip_id=2366",
    "scraper_type": "html",
    "active": true,
    "seed_source_id": "carson-city-board-of-supervisors",
    "notes": "Discovered from Parks and Recreation Commission historical meeting archive.",
    "created_at": "2026-06-17T23:56:08.004Z",
    "updated_at": "2026-06-17T23:56:08.004Z"
  },
  {
    "id": "body-carson-city-board-of-supervisors-growth-management-commission-and-planning-commission",
    "name": "Growth Management Commission and Planning Commission",
    "jurisdiction": "Carson City, NV",
    "level": "city",
    "website": null,
    "source_url": "https://carsoncity.granicus.com/AgendaViewer.php?view_id=2&clip_id=2677",
    "meeting_index_url": "https://carsoncity.granicus.com/AgendaViewer.php?view_id=2&clip_id=2677",
    "scraper_type": "html",
    "active": true,
    "seed_source_id": "carson-city-board-of-supervisors",
    "notes": "Discovered from Growth Management Commission and Planning Commission historical meeting archive.",
    "created_at": "2026-06-17T23:56:08.004Z",
    "updated_at": "2026-06-17T23:56:08.004Z"
  },
  {
    "id": "body-carson-city-board-of-supervisors-planning-commission",
    "name": "Planning Commission",
    "jurisdiction": "Carson City, NV",
    "level": "city",
    "website": null,
    "source_url": "https://carsoncity.granicus.com/AgendaViewer.php?view_id=2&clip_id=2362",
    "meeting_index_url": "https://carsoncity.granicus.com/AgendaViewer.php?view_id=2&clip_id=2362",
    "scraper_type": "html",
    "active": true,
    "seed_source_id": "carson-city-board-of-supervisors",
    "notes": "Discovered from Planning Commission historical meeting archive.",
    "created_at": "2026-06-17T23:56:08.004Z",
    "updated_at": "2026-06-17T23:56:08.004Z"
  },
  {
    "id": "body-carson-city-board-of-supervisors-planning-commission-workshop",
    "name": "Planning Commission Workshop",
    "jurisdiction": "Carson City, NV",
    "level": "city",
    "website": null,
    "source_url": "https://carsoncity.granicus.com/AgendaViewer.php?view_id=2&clip_id=2527",
    "meeting_index_url": "https://carsoncity.granicus.com/AgendaViewer.php?view_id=2&clip_id=2527",
    "scraper_type": "html",
    "active": true,
    "seed_source_id": "carson-city-board-of-supervisors",
    "notes": "Discovered from Planning Commission Workshop historical meeting archive.",
    "created_at": "2026-06-17T23:56:08.004Z",
    "updated_at": "2026-06-17T23:56:08.004Z"
  },
  {
    "id": "body-carson-city-board-of-supervisors-growth-management-and-planning-commission",
    "name": "Growth Management and Planning Commission",
    "jurisdiction": "Carson City, NV",
    "level": "city",
    "website": null,
    "source_url": "https://carsoncity.granicus.com/AgendaViewer.php?view_id=2&clip_id=2431",
    "meeting_index_url": "https://carsoncity.granicus.com/AgendaViewer.php?view_id=2&clip_id=2431",
    "scraper_type": "html",
    "active": true,
    "seed_source_id": "carson-city-board-of-supervisors",
    "notes": "Discovered from Growth Management and Planning Commission historical meeting archive.",
    "created_at": "2026-06-17T23:56:08.004Z",
    "updated_at": "2026-06-17T23:56:08.004Z"
  },
  {
    "id": "body-carson-city-board-of-supervisors-redevelopment-authority-citizens-committee",
    "name": "Redevelopment Authority Citizens Committee",
    "jurisdiction": "Carson City, NV",
    "level": "city",
    "website": null,
    "source_url": "https://carsoncity.granicus.com/AgendaViewer.php?view_id=2&clip_id=2386",
    "meeting_index_url": "https://carsoncity.granicus.com/AgendaViewer.php?view_id=2&clip_id=2386",
    "scraper_type": "html",
    "active": true,
    "seed_source_id": "carson-city-board-of-supervisors",
    "notes": "Discovered from Redevelopment Authority Citizens Committee historical meeting archive.",
    "created_at": "2026-06-17T23:56:08.004Z",
    "updated_at": "2026-06-17T23:56:08.004Z"
  },
  {
    "id": "body-carson-city-board-of-supervisors-regional-transportation-commission",
    "name": "Regional Transportation Commission",
    "jurisdiction": "Carson City, NV",
    "level": "city",
    "website": null,
    "source_url": "https://carsoncity.granicus.com/AgendaViewer.php?view_id=2&clip_id=2375",
    "meeting_index_url": "https://carsoncity.granicus.com/AgendaViewer.php?view_id=2&clip_id=2375",
    "scraper_type": "html",
    "active": true,
    "seed_source_id": "carson-city-board-of-supervisors",
    "notes": "Discovered from Regional Transportation Commission historical meeting archive.",
    "created_at": "2026-06-17T23:56:08.004Z",
    "updated_at": "2026-06-17T23:56:08.004Z"
  },
  {
    "id": "body-carson-city-board-of-supervisors-regional-transportation-commission-rtc",
    "name": "Regional Transportation Commission (RTC)",
    "jurisdiction": "Carson City, NV",
    "level": "city",
    "website": null,
    "source_url": "https://carsoncity.granicus.com/AgendaViewer.php?view_id=2&clip_id=2352",
    "meeting_index_url": "https://carsoncity.granicus.com/AgendaViewer.php?view_id=2&clip_id=2352",
    "scraper_type": "html",
    "active": true,
    "seed_source_id": "carson-city-board-of-supervisors",
    "notes": "Discovered from Regional Transportation Commission (RTC) historical meeting archive.",
    "created_at": "2026-06-17T23:56:08.004Z",
    "updated_at": "2026-06-17T23:56:08.004Z"
  },
  {
    "id": "body-carson-city-board-of-supervisors-utility-finance-oversight-committee",
    "name": "Utility Finance Oversight Committee",
    "jurisdiction": "Carson City, NV",
    "level": "city",
    "website": null,
    "source_url": "https://carsoncity.granicus.com/AgendaViewer.php?view_id=2&clip_id=2405",
    "meeting_index_url": "https://carsoncity.granicus.com/AgendaViewer.php?view_id=2&clip_id=2405",
    "scraper_type": "html",
    "active": true,
    "seed_source_id": "carson-city-board-of-supervisors",
    "notes": "Discovered from Utility Finance Oversight Committee historical meeting archive.",
    "created_at": "2026-06-17T23:56:08.004Z",
    "updated_at": "2026-06-17T23:56:08.004Z"
  },
  {
    "id": "body-washoe-county-commission-board-of-county-commissioners",
    "name": "Board of County Commissioners",
    "jurisdiction": "Washoe County, NV",
    "level": "county",
    "website": null,
    "source_url": "https://washoe-nv.legistar.com/MeetingDetail.aspx?GUID=E6A3DAF3-5735-4CFF-B40F-8727651BE849&ID=1347265&Search=",
    "meeting_index_url": "https://washoe-nv.legistar.com/MeetingDetail.aspx?GUID=E6A3DAF3-5735-4CFF-B40F-8727651BE849&ID=1347265&Search=",
    "scraper_type": "html",
    "active": true,
    "seed_source_id": "washoe-county-commission",
    "notes": "Discovered from Board of County Commissioners historical meeting archive.",
    "created_at": "2026-06-17T23:56:08.004Z",
    "updated_at": "2026-06-17T23:56:08.004Z"
  },
  {
    "id": "body-washoe-county-school-district-washoe-county-school-district-board-of-trustees",
    "name": "Washoe County School District Board of Trustees",
    "jurisdiction": "Washoe County School District, NV",
    "level": "school",
    "website": null,
    "source_url": "https://washoeschools.community.diligentoneplatform.com/Portal/MeetingInformation.aspx?Org=Cal&Id=1357",
    "meeting_index_url": "https://washoeschools.community.diligentoneplatform.com/Portal/MeetingInformation.aspx?Org=Cal&Id=1357",
    "scraper_type": "html",
    "active": true,
    "seed_source_id": "washoe-county-school-district",
    "notes": "Discovered from Washoe County School District Board of Trustees historical meeting archive.",
    "created_at": "2026-06-17T23:56:08.005Z",
    "updated_at": "2026-06-17T23:56:08.005Z"
  },
  {
    "id": "body-manual-reno-city-council-reno-city-council",
    "name": "Reno City Council",
    "jurisdiction": "Reno, NV",
    "level": "city",
    "website": "https://reno.primegov.com/public/portal",
    "source_url": "https://reno.primegov.com/public/portal",
    "meeting_index_url": "https://reno.primegov.com/public/portal",
    "scraper_type": "manual",
    "active": true,
    "seed_source_id": "reno-city-council",
    "notes": "Manual browser-assisted cache source. Imported from saved official public records.",
    "created_at": "2026-06-17T23:56:12.773Z",
    "updated_at": "2026-06-17T23:56:12.773Z"
  },
  {
    "id": "body-manual-nv-legislature-nevada-legislature",
    "name": "Nevada Legislature",
    "jurisdiction": "Nevada",
    "level": "state",
    "website": "https://www.leg.state.nv.us/App/Calendar/A/",
    "source_url": "https://www.leg.state.nv.us/App/Calendar/A/",
    "meeting_index_url": "https://www.leg.state.nv.us/App/Calendar/A/",
    "scraper_type": "manual",
    "active": true,
    "seed_source_id": "nv-legislature",
    "notes": "Manual browser-assisted cache source. Imported from saved official public records.",
    "created_at": "2026-06-17T23:56:12.845Z",
    "updated_at": "2026-06-17T23:56:12.845Z"
  },
  {
    "id": "body-manual-nv-senate-nevada-senate",
    "name": "Nevada Senate",
    "jurisdiction": "Nevada",
    "level": "state",
    "website": "https://www.leg.state.nv.us/",
    "source_url": "https://www.leg.state.nv.us/",
    "meeting_index_url": "https://www.leg.state.nv.us/",
    "scraper_type": "manual",
    "active": true,
    "seed_source_id": "nv-senate",
    "notes": "Manual browser-assisted cache source. Imported from saved official public records.",
    "created_at": "2026-06-17T23:56:12.848Z",
    "updated_at": "2026-06-17T23:56:12.848Z"
  },
  {
    "id": "body-manual-nv-assembly-nevada-assembly",
    "name": "Nevada Assembly",
    "jurisdiction": "Nevada",
    "level": "state",
    "website": "https://www.leg.state.nv.us/",
    "source_url": "https://www.leg.state.nv.us/",
    "meeting_index_url": "https://www.leg.state.nv.us/",
    "scraper_type": "manual",
    "active": true,
    "seed_source_id": "nv-assembly",
    "notes": "Manual browser-assisted cache source. Imported from saved official public records.",
    "created_at": "2026-06-17T23:56:12.853Z",
    "updated_at": "2026-06-17T23:56:12.853Z"
  },
  {
    "id": "body-manual-nv-governor-executive-boards-nevada-boards-and-commissions",
    "name": "Nevada Boards and Commissions",
    "jurisdiction": "Nevada",
    "level": "state",
    "website": "https://www.gov.nv.gov/board-appts/",
    "source_url": "https://www.gov.nv.gov/board-appts/",
    "meeting_index_url": "https://www.gov.nv.gov/board-appts/",
    "scraper_type": "manual",
    "active": true,
    "seed_source_id": "nv-governor-executive-boards",
    "notes": "Manual browser-assisted cache source. Imported from saved official public records.",
    "created_at": "2026-06-17T23:56:12.854Z",
    "updated_at": "2026-06-17T23:56:12.854Z"
  },
  {
    "id": "body-manual-sparks-city-council-sparks-city-council",
    "name": "Sparks City Council",
    "jurisdiction": "Sparks, NV",
    "level": "city",
    "website": "https://www.cityofsparks.us/your_government/departments/city_clerk_and_records_management/city_council_meeting_agendas_and_minutes/index.php",
    "source_url": "https://www.cityofsparks.us/your_government/departments/city_clerk_and_records_management/city_council_meeting_agendas_and_minutes/index.php",
    "meeting_index_url": "https://www.cityofsparks.us/your_government/departments/city_clerk_and_records_management/city_council_meeting_agendas_and_minutes/index.php",
    "scraper_type": "manual",
    "active": true,
    "seed_source_id": "sparks-city-council",
    "notes": "Manual browser-assisted cache source. Imported from saved official public records.",
    "created_at": "2026-06-17T23:56:12.858Z",
    "updated_at": "2026-06-17T23:56:12.858Z"
  },
  {
    "id": "body-manual-clark-county-commission-clark-county-commission",
    "name": "Clark County Commission",
    "jurisdiction": "Clark County, NV",
    "level": "county",
    "website": "https://clark.legistar.com/",
    "source_url": "https://clark.legistar.com/",
    "meeting_index_url": "https://clark.legistar.com/",
    "scraper_type": "manual",
    "active": true,
    "seed_source_id": "clark-county-commission",
    "notes": "Manual browser-assisted cache source. Imported from saved official public records.",
    "created_at": "2026-06-17T23:56:12.892Z",
    "updated_at": "2026-06-17T23:56:12.892Z"
  },
  {
    "id": "body-manual-las-vegas-city-council-las-vegas-city-council",
    "name": "Las Vegas City Council",
    "jurisdiction": "Las Vegas, NV",
    "level": "city",
    "website": "https://lasvegas.primegov.com/public/portal",
    "source_url": "https://lasvegas.primegov.com/public/portal",
    "meeting_index_url": "https://lasvegas.primegov.com/public/portal",
    "scraper_type": "manual",
    "active": true,
    "seed_source_id": "las-vegas-city-council",
    "notes": "Manual browser-assisted cache source. Imported from saved official public records.",
    "created_at": "2026-06-17T23:56:14.506Z",
    "updated_at": "2026-06-17T23:56:14.506Z"
  },
  {
    "id": "body-manual-henderson-city-council-henderson-city-council",
    "name": "Henderson City Council",
    "jurisdiction": "Henderson, NV",
    "level": "city",
    "website": "https://www.cityofhenderson.com/government/public-meeting-agendas",
    "source_url": "https://www.cityofhenderson.com/government/public-meeting-agendas",
    "meeting_index_url": "https://www.cityofhenderson.com/government/public-meeting-agendas",
    "scraper_type": "manual",
    "active": true,
    "seed_source_id": "henderson-city-council",
    "notes": "Manual browser-assisted cache source. Imported from saved official public records.",
    "created_at": "2026-06-17T23:56:14.531Z",
    "updated_at": "2026-06-17T23:56:14.531Z"
  },
  {
    "id": "body-manual-north-las-vegas-city-council-north-las-vegas-city-council",
    "name": "North Las Vegas City Council",
    "jurisdiction": "North Las Vegas, NV",
    "level": "city",
    "website": "https://www.cityofnorthlasvegas.com/our-city/meetings-and-agendas",
    "source_url": "https://www.cityofnorthlasvegas.com/our-city/meetings-and-agendas",
    "meeting_index_url": "https://www.cityofnorthlasvegas.com/our-city/meetings-and-agendas",
    "scraper_type": "manual",
    "active": true,
    "seed_source_id": "north-las-vegas-city-council",
    "notes": "Manual browser-assisted cache source. Imported from saved official public records.",
    "created_at": "2026-06-17T23:56:17.116Z",
    "updated_at": "2026-06-17T23:56:17.116Z"
  },
  {
    "id": "body-manual-clark-county-school-district-clark-county-school-district-board-of-trustees",
    "name": "Clark County School District Board of Trustees",
    "jurisdiction": "Clark County School District, NV",
    "level": "school",
    "website": "https://www.boarddocs.com/nv/ccsdlv/Board.nsf/Public",
    "source_url": "https://www.boarddocs.com/nv/ccsdlv/Board.nsf/Public",
    "meeting_index_url": "https://www.boarddocs.com/nv/ccsdlv/Board.nsf/Public",
    "scraper_type": "manual",
    "active": true,
    "seed_source_id": "clark-county-school-district",
    "notes": "Manual browser-assisted cache source. Imported from saved official public records.",
    "created_at": "2026-06-17T23:56:17.383Z",
    "updated_at": "2026-06-17T23:56:17.383Z"
  },
  {
    "id": "body-manual-carson-city-school-district-carson-city-school-district-board-of-trustees",
    "name": "Carson City School District Board of Trustees",
    "jurisdiction": "Carson City School District, NV",
    "level": "school",
    "website": "https://www.carsoncityschools.com/our-district/school-board",
    "source_url": "https://www.carsoncityschools.com/our-district/school-board",
    "meeting_index_url": "https://www.carsoncityschools.com/our-district/school-board",
    "scraper_type": "manual",
    "active": true,
    "seed_source_id": "carson-city-school-district",
    "notes": "Manual browser-assisted cache source. Imported from saved official public records.",
    "created_at": "2026-06-17T23:56:17.385Z",
    "updated_at": "2026-06-17T23:56:17.385Z"
  },
  {
    "id": "body-manual-nshe-board-of-regents-nevada-system-of-higher-education-board-of-regents",
    "name": "Nevada System of Higher Education Board of Regents",
    "jurisdiction": "Nevada System of Higher Education",
    "level": "university",
    "website": "https://nshe.nevada.edu/regents/upcoming-meetings/",
    "source_url": "https://nshe.nevada.edu/regents/upcoming-meetings/",
    "meeting_index_url": "https://nshe.nevada.edu/regents/upcoming-meetings/",
    "scraper_type": "manual",
    "active": true,
    "seed_source_id": "nshe-board-of-regents",
    "notes": "Manual browser-assisted cache source. Imported from saved official public records.",
    "created_at": "2026-06-17T23:56:19.009Z",
    "updated_at": "2026-06-17T23:56:19.009Z"
  }
]
